{
    "mesh": {
        "triangle_list": [
            [
                0,
                1,
                2
            ],
            [
                0,
                2,
                3
            ],
            [
                0,
                3,
                4
            ],
            [
                4,
                5,
                0
            ],
            [
                2,
                1,
                6
            ],
            [
                2,
                6,
                7
            ],
            [
                7,
                8,
                2
            ]
        ],
        "vertex_list": [
            {
                "x": 1.6339745962155623,
                "y": 0.3660254037844379
            },
            {
                "x": 2.0,
                "y": 0.0
            },
            {
                "x": 3.0,
                "y": 1.7320508075688776
            },
            {
                "x": 2.5000000000000004,
                "y": 1.8660254037844386
            },
            {
                "x": 2.0,
                "y": 1.7320508075688776
            },
            {
                "x": 1.5000000000000004,
                "y": 0.8660254037844395
            },
            {
                "x": 3.0,
                "y": 0.0
            },
            {
                "x": 3.366025403784438,
                "y": 0.36602540378443793
            },
            {
                "x": 3.4999999999999996,
                "y": 0.8660254037844392
            }
        ]
    }
}